etlplus/README.md
etlplus/__init__.py
etlplus/__main__.py
etlplus/__version__.py
etlplus/config.py
etlplus/enums.py
etlplus/mixins.py
etlplus/py.typed
etlplus/types.py
etlplus/utils.py
etlplus/api/README.md
etlplus/api/__init__.py
etlplus/api/auth.py
etlplus/api/config.py
etlplus/api/endpoint_client.py
etlplus/api/enums.py
etlplus/api/errors.py
etlplus/api/request_manager.py
etlplus/api/retry_manager.py
etlplus/api/transport.py
etlplus/api/types.py
etlplus/api/utils.py
etlplus/api/pagination/__init__.py
etlplus/api/pagination/client.py
etlplus/api/pagination/config.py
etlplus/api/pagination/paginator.py
etlplus/api/rate_limiting/__init__.py
etlplus/api/rate_limiting/config.py
etlplus/api/rate_limiting/rate_limiter.py
etlplus/cli/README.md
etlplus/cli/__init__.py
etlplus/cli/commands.py
etlplus/cli/constants.py
etlplus/cli/handlers.py
etlplus/cli/io.py
etlplus/cli/main.py
etlplus/cli/options.py
etlplus/cli/state.py
etlplus/cli/types.py
etlplus/connector/__init__.py
etlplus/connector/api.py
etlplus/connector/connector.py
etlplus/connector/core.py
etlplus/connector/database.py
etlplus/connector/enums.py
etlplus/connector/file.py
etlplus/connector/types.py
etlplus/connector/utils.py
etlplus/database/README.md
etlplus/database/__init__.py
etlplus/database/ddl.py
etlplus/database/engine.py
etlplus/database/orm.py
etlplus/database/schema.py
etlplus/database/types.py
etlplus/file/README.md
etlplus/file/__init__.py
etlplus/file/_imports.py
etlplus/file/_io.py
etlplus/file/accdb.py
etlplus/file/arrow.py
etlplus/file/avro.py
etlplus/file/bson.py
etlplus/file/cbor.py
etlplus/file/cfg.py
etlplus/file/conf.py
etlplus/file/core.py
etlplus/file/csv.py
etlplus/file/dat.py
etlplus/file/dta.py
etlplus/file/duckdb.py
etlplus/file/enums.py
etlplus/file/feather.py
etlplus/file/fwf.py
etlplus/file/gz.py
etlplus/file/hbs.py
etlplus/file/hdf5.py
etlplus/file/ini.py
etlplus/file/ion.py
etlplus/file/jinja2.py
etlplus/file/json.py
etlplus/file/log.py
etlplus/file/mat.py
etlplus/file/mdb.py
etlplus-0.16.4.dist-info/licenses/LICENSE
etlplus-0.16.4.dist-info/METADATA
etlplus-0.16.4.dist-info/WHEEL
etlplus-0.16.4.dist-info/entry_points.txt
etlplus-0.16.4.dist-info/top_level.txt
etlplus-0.16.4.dist-info/RECORD
