Metadata-Version: 2.4
Name: etlplus
Version: 0.16.4
Summary: A Swiss Army knife for simple ETL operations
Home-page: https://github.com/Dagitali/ETLPlus
Author: ETLPlus Team
License: MIT
Project-URL: Homepage, https://github.com/Dagitali/ETLPlus
Project-URL: Repository, https://github.com/Dagitali/ETLPlus
Classifier: Development Status :: 3 - Alpha
Classifier: Intended Audience :: Developers
Classifier: Topic :: Software Development :: Libraries :: Python Modules
Classifier: License :: OSI Approved :: MIT License
Classifier: Programming Language :: Python :: 3
Classifier: Programming Language :: Python :: 3.13
Classifier: Programming Language :: Python :: 3.14
Requires-Python: >=3.13,<3.15
License-File: LICENSE
Requires-Dist: fastavro>=1.12.1
Requires-Dist: jinja2>=3.1.6
Requires-Dist: openpyxl>=3.1.5
Requires-Dist: pyodbc>=5.3.0
Requires-Dist: pyarrow>=22.0.0
Requires-Dist: python-dotenv>=1.2.1
Requires-Dist: pandas>=2.3.3
Requires-Dist: pydantic>=2.12.5
Requires-Dist: PyYAML>=6.0.3
Requires-Dist: requests>=2.32.5
Requires-Dist: SQLAlchemy>=2.0.45
Requires-Dist: typer>=0.21.0
Requires-Dist: xlrd>=2.0.2
Requires-Dist: xlwt>=1.3.0
Provides-Extra: dev
Requires-Dist: black>=25.9.0; extra == "dev"
Requires-Dist: build>=1.2.2; extra == "dev"
Requires-Dist: flake8>=7.3.0; extra == "dev"
Requires-Dist: PyYAML>=6.0.3; extra == "dev"
Requires-Dist: pydoclint>=0.8.1; extra == "dev"
Requires-Dist: pydocstyle>=6.3.0; extra == "dev"
Requires-Dist: pytest>=8.4.2; extra == "dev"
Requires-Dist: pytest-cov>=7.0.0; extra == "dev"
Requires-Dist: ruff>=0.14.4; extra == "dev"
Provides-Extra: docs
Requires-Dist: sphinx>=4.0.0; extra == "docs"
Requires-Dist: sphinx-rtd-theme>=1.0.0; extra == "docs"
Dynamic: home-page
Dynamic: license-file
Dynamic: requires-python
